{
    "Features.ColourCorrection.Dialogue.Title":  "Kleurcorrectie",
    "Features.ColourCorrection.Description":  "Helpt mensen met slecht zicht, lichtgevoeligheid of kleurenblindheid. Spelen met de kleurinstellingen kan alles een warme of koele tint geven.",
    "Features.ColourCorrection.Dialogue.lblEnabled":  "Ingeschakeld:",
    "Features.ColourCorrection.Dialogue.lblEnabled.HoverText":  "Schakelt de kleurcorrectie-shader aan.",
    "Features.ColourCorrection.Dialogue.lblPreset":  "Preset:",
    "Features.ColourCorrection.Dialogue.lblPreset.HoverText":  "Simuleert een specifiek type kleurenzichtstoornis.",
    "Features.ColourCorrection.Dialogue.lblRedBalance":  "Rode balans:",
    "Features.ColourCorrection.Dialogue.lblRedBalance.HoverText":  "Verandert hoeveel rood je op de scène moet aanbrengen.",
    "Features.ColourCorrection.Dialogue.lblGreenBalance":  "Groene Balans:",
    "Features.ColourCorrection.Dialogue.lblGreenBalance.HoverText":  "Verandert hoeveel Groen je op de scène moet toepassen.",
    "Features.ColourCorrection.Dialogue.lblBlueBalance":  "Blauw Saldo:",
    "Features.ColourCorrection.Dialogue.lblBlueBalance.HoverText":  "Verandert hoeveel blauw je op de scène moet aanbrengen.",
    "Features.ColourCorrection.Dialogue.lblSaturation":  "Verzadiging:",
    "Features.ColourCorrection.Dialogue.lblSaturation.HoverText":  "Verandert de kleurverzadiging van de scène. Lagere waarden doen kleuren vervagen, hogere waarden maken kleuren levendiger.",
    "Features.ColourCorrection.Dialogue.btnReset":  "Waarden resetten",
    "Features.ColourCorrection.Dialogue.Presets.Trichromacy":  "Trichromatie",
    "Features.ColourCorrection.Dialogue.Presets.Protanopia":  "Protanopie",
    "Features.ColourCorrection.Dialogue.Presets.Deuteranopia":  "Deuteranopie",
    "Features.ColourCorrection.Dialogue.Presets.Tritanopia":  "Tritanopia",
    "Features.ColourCorrection.Dialogue.Presets.Protanomaly":  "Protanomalie",
    "Features.ColourCorrection.Dialogue.Presets.Deuteranomaly":  "Deuteranolie",
    "Features.ColourCorrection.Dialogue.Presets.Tritanomaly":  "Tritanomalie",
    "Features.ColourCorrection.Dialogue.Presets.Achromatopsia":  "Achromatopsie",
    "Features.ColourCorrection.Dialogue.Presets.Achromatomaly":  "Achromatomalie"
}
