{
    "Features.ColourCorrection.Dialogue.lblBlueBalance.HoverText":  "Sahneye ne kadar Mavi uygulanacağını değiştirir.",
    "Features.ColourCorrection.Dialogue.Presets.Achromatopsia":  "Akromatopsi",
    "Features.ColourCorrection.Dialogue.lblEnabled.HoverText":  "Renk düzeltme gölgelendiricisini değiştirir.",
    "Features.ColourCorrection.Dialogue.lblEnabled":  "Etkin:",
    "Features.ColourCorrection.Dialogue.lblRedBalance":  "Kırmızı Dengesi:",
    "Features.ColourCorrection.Dialogue.lblPreset":  "Ön ayar:",
    "Features.ColourCorrection.Dialogue.btnReset":  "Değerleri Sıfırla",
    "Features.ColourCorrection.Dialogue.lblGreenBalance":  "Yeşil Denge:",
    "Features.ColourCorrection.Dialogue.Presets.Protanomaly":  "Protanomali",
    "Features.ColourCorrection.Dialogue.Presets.Protanopia":  "Protanopia",
    "Features.ColourCorrection.Dialogue.lblRedBalance.HoverText":  "Sahneye ne kadar Kırmızı uygulanacağını değiştirir.",
    "Features.ColourCorrection.Dialogue.lblSaturation":  "Doygunluk:",
    "Features.ColourCorrection.Dialogue.lblSaturation.HoverText":  "Sahnenin renk doygunluğunu değiştirir. Daha düşük değerler renkleri soldurur, daha yüksek değerler renkleri daha canlı hale getirir.",
    "Features.ColourCorrection.Dialogue.Presets.Trichromacy":  "Trikromati",
    "Features.ColourCorrection.Dialogue.Title":  "Renk Düzeltme",
    "Features.ColourCorrection.Dialogue.lblPreset.HoverText":  "Belirli bir renk görme eksikliği türünü simüle eder.",
    "Features.ColourCorrection.Dialogue.lblGreenBalance.HoverText":  "Sahneye ne kadar Yeşil uygulanacağını değiştirir.",
    "Features.ColourCorrection.Dialogue.Presets.Tritanopia":  "Tritanopi (Tritanopi)",
    "Features.ColourCorrection.Dialogue.Presets.Deuteranopia":  "Deuteranopia",
    "Features.ColourCorrection.Dialogue.Presets.Achromatomaly":  "Akromatomi",
    "Features.ColourCorrection.Dialogue.Presets.Tritanomaly":  "Tritanomali",
    "Features.ColourCorrection.Dialogue.Presets.Deuteranomaly":  "Deuteranomaly",
    "Features.ColourCorrection.Dialogue.lblBlueBalance":  "Mavi Dengesi:",
    "Features.ColourCorrection.Description":  "Zayıf görme, ışık hassasiyeti veya renk körlüğü olan kişilere yardımcı olur. Renk ayarlarıyla oynamak, her şeye sıcak veya soğuk bir renk verebilir."
}
